iterapi/__init__.py
iterapi/iterapi.py
iterapi-1.2.7.dist-info/LICENSE
iterapi-1.2.7.dist-info/METADATA
iterapi-1.2.7.dist-info/WHEEL
iterapi-1.2.7.dist-info/top_level.txt
iterapi-1.2.7.dist-info/RECORD
