Metadata-Version: 2.1
Name: iterapi
Version: 1.2.7
Summary: Python API to student portal of ITER
Home-page: https://github.com/SubhrajitPrusty/iterapi
Author: Subhrajit Prusty
Author-email: subhrajit1997@gmail.com
License: MIT
Keywords: api ITER development
Classifier: Development Status :: 4 - Beta
Classifier: Intended Audience :: Developers
Classifier: Topic :: Software Development :: Build Tools
Classifier: License :: OSI Approved :: MIT License
Classifier: Programming Language :: Python :: 3
Classifier: Programming Language :: Python :: 3.4
Classifier: Programming Language :: Python :: 3.5
Classifier: Programming Language :: Python :: 3.6
License-File: LICENSE
Requires-Dist: requests
